{
  "c3": {
    "created_at": "2013-07-18T06:51:40Z",
    "description": "A D3-based reusable chart library",
    "forks": 1197,
    "language": "JavaScript",
    "name": "c3",
    "open_issues": 855,
    "size": 7326,
    "stargazers_count": 7350,
    "url": "https://api.github.com/repos/c3js/c3",
    "watchers": 7350
  },
  "d3.chart": {
    "created_at": "2013-02-22T19:24:27Z",
    "description": "A framework for creating reusable charts with d3.js.",
    "forks": 94,
    "language": "JavaScript",
    "name": "d3.chart",
    "open_issues": 30,
    "size": 711,
    "stargazers_count": 751,
    "url": "https://api.github.com/repos/misoproject/d3.chart",
    "watchers": 751
  },
  "d3fc": {
    "created_at": "2014-10-06T15:03:11Z",
    "description": "A collection of components that make it easy to build interactive charts with D3",
    "forks": 59,
    "language": "JavaScript",
    "name": "d3fc",
    "open_issues": 50,
    "size": 6465,
    "stargazers_count": 376,
    "url": "https://api.github.com/repos/d3fc/d3fc",
    "watchers": 376
  },
  "d3plus": {
    "created_at": "2013-01-09T00:26:58Z",
    "description": "A javascript library that extends D3.js to enable fast and beautiful visualizations.",
    "forks": 174,
    "language": "JavaScript",
    "name": "d3plus",
    "open_issues": 259,
    "size": 33625,
    "stargazers_count": 1341,
    "url": "https://api.github.com/repos/alexandersimoes/d3plus",
    "watchers": 1341
  },
  "d4": {
    "created_at": "2014-01-27T18:04:54Z",
    "description": "A friendly reusable charts DSL for D3",
    "forks": 43,
    "language": "JavaScript",
    "name": "d4",
    "open_issues": 18,
    "size": 2758,
    "stargazers_count": 403,
    "url": "https://api.github.com/repos/heavysixer/d4",
    "watchers": 403
  },
  "dc.js": {
    "created_at": "2012-06-19T14:20:30Z",
    "description": "Multi-Dimensional charting built to work natively with crossfilter rendered with d3.js",
    "forks": 1613,
    "language": "JavaScript",
    "name": "dc.js",
    "open_issues": 342,
    "size": 35969,
    "stargazers_count": 5996,
    "url": "https://api.github.com/repos/dc-js/dc.js",
    "watchers": 5996
  },
  "epoch": {
    "created_at": "2013-06-27T23:04:32Z",
    "description": "A general purpose, real-time visualization library.",
    "forks": 288,
    "language": "HTML",
    "name": "epoch",
    "open_issues": 64,
    "size": 2131,
    "stargazers_count": 4899,
    "url": "https://api.github.com/repos/epochjs/epoch",
    "watchers": 4899
  },
  "forest-d3": {
    "created_at": "2015-06-11T12:49:26Z",
    "description": "My attempt at implementing a better time series charting library, based on d3.js",
    "forks": 1,
    "language": "CoffeeScript",
    "name": "forest-d3",
    "open_issues": 18,
    "size": 473,
    "stargazers_count": 51,
    "url": "https://api.github.com/repos/robinfhu/forest-d3",
    "watchers": 51
  },
  "kotojs": {
    "created_at": "2015-09-28T19:40:36Z",
    "description": "A framework for building reusable components with d3.js",
    "forks": 15,
    "language": "JavaScript",
    "name": "kotojs",
    "open_issues": 5,
    "size": 3238,
    "stargazers_count": 276,
    "url": "https://api.github.com/repos/kotojs/kotojs",
    "watchers": 276
  },
  "metrics-graphics": {
    "created_at": "2014-05-01T18:25:52Z",
    "description": "A library optimized for concise and principled data graphics and layouts.",
    "forks": 444,
    "language": "JavaScript",
    "name": "metrics-graphics",
    "open_issues": 128,
    "size": 5811,
    "stargazers_count": 6769,
    "url": "https://api.github.com/repos/mozilla/metrics-graphics",
    "watchers": 6769
  },
  "null": {},
  "nvd3": {
    "created_at": "2012-11-15T18:51:59Z",
    "description": "A reusable charting library written in d3.js",
    "forks": 2112,
    "language": "JavaScript",
    "name": "nvd3",
    "open_issues": 517,
    "size": 15954,
    "stargazers_count": 6279,
    "url": "https://api.github.com/repos/novus/nvd3",
    "watchers": 6279
  },
  "plotly.js": {
    "created_at": "2015-11-05T23:27:17Z",
    "description": "The open source JavaScript graphing library that powers plotly",
    "forks": 798,
    "language": "JavaScript",
    "name": "plotly.js",
    "open_issues": 428,
    "size": 342464,
    "stargazers_count": 7257,
    "url": "https://api.github.com/repos/plotly/plotly.js",
    "watchers": 7257
  },
  "plottable": {
    "created_at": "2014-01-22T19:29:19Z",
    "description": ":bar_chart: A library of modular chart components built on D3",
    "forks": 186,
    "language": "TypeScript",
    "name": "plottable",
    "open_issues": 292,
    "size": 75177,
    "stargazers_count": 2251,
    "url": "https://api.github.com/repos/palantir/plottable",
    "watchers": 2251
  },
  "rickshaw": {
    "created_at": "2011-10-20T22:02:37Z",
    "description": " JavaScript toolkit for creating interactive real-time graphs",
    "forks": 965,
    "language": "JavaScript",
    "name": "rickshaw",
    "open_issues": 205,
    "size": 2184,
    "stargazers_count": 6161,
    "url": "https://api.github.com/repos/shutterstock/rickshaw",
    "watchers": 6161
  },
  "vega": {
    "created_at": "2013-02-03T18:36:30Z",
    "description": "A visualization grammar.",
    "forks": 600,
    "language": "HTML",
    "name": "vega",
    "open_issues": 140,
    "size": 48245,
    "stargazers_count": 5444,
    "url": "https://api.github.com/repos/vega/vega",
    "watchers": 5444
  }
}